AUTHORS
LICENSE
MANIFEST.in
README
setup.cfg
setup.py
docs/Makefile
docs/changelog.rst
docs/conf.py
docs/index.rst
docs/make.bat
docs/_static/debugtoolbar.png
docs/_themes/README
docs/_themes/flask_theme_support.py
docs/_themes/flask/theme.conf
docs/_themes/flask/static/flasky.css_t
docs/_themes/flask_small/layout.html
docs/_themes/flask_small/theme.conf
docs/_themes/flask_small/static/flasky.css_t
flask_mongoengine/__init__.py
flask_mongoengine/json.py
flask_mongoengine/operation_tracker.py
flask_mongoengine/pagination.py
flask_mongoengine/panels.py
flask_mongoengine/sessions.py
flask_mongoengine/templates/panels/mongo-panel.html
flask_mongoengine/wtf/__init__.py
flask_mongoengine/wtf/base.py
flask_mongoengine/wtf/fields.py
flask_mongoengine/wtf/models.py
flask_mongoengine/wtf/orm.py
quokka_flask_mongoengine.egg-info/PKG-INFO
quokka_flask_mongoengine.egg-info/SOURCES.txt
quokka_flask_mongoengine.egg-info/dependency_links.txt
quokka_flask_mongoengine.egg-info/not-zip-safe
quokka_flask_mongoengine.egg-info/requires.txt
quokka_flask_mongoengine.egg-info/top_level.txt