Metadata-Version: 1.1
Name: quokka-flask-mongoengine
Version: 0.7.4
Summary: Fork of Flask support for MongoDB and with WTF model forms
Home-page: https://github.com/mongoengine/flask-mongoengine
Author: Ross Lawley
Author-email: ross.lawley@gmail.com
License: BSD
Platform: any
Classifier: Development Status :: 4 - Beta
Classifier: Environment :: Web Environment
Classifier: Intended Audience :: Developers
Classifier: License :: OSI Approved :: BSD License
Classifier: Operating System :: OS Independent
Classifier: Programming Language :: Python
Classifier: Topic :: Internet :: WWW/HTTP :: Dynamic Content
Classifier: Topic :: Software Development :: Libraries :: Python Modules
